[{"name": "iPhone 17 Pro", "desc": "iPhone 17, newest version, with increased capabilities from Pro specification", "sku": "APP1700", "price": 13.99, "tags": ["apple", "phone"], "available": true}, {"name": "iPhone 16", "desc": "Second-last generation of iPhone, standard model.", "sku": "APN1600", "price": 13.99, "tags": ["apple", "phone"], "available": true}, {"name": "iPhone 13", "desc": "Older version of iPhone, standard model.", "sku": "APN1300", "price": 13.99, "tags": ["apple", "phone"], "available": true}, {"name": "iPhone X Pro Max", "desc": "Highest specs (Pro Max) version of 10th iPhone, named X after the Roman numeral.", "sku": "APPm1000", "price": 13.99, "tags": ["apple", "phone"], "available": true}, {"name": "iPad Air 2", "desc": "Second-generation small Apple tablet", "sku": "ATA0200", "price": 13.99, "tags": ["apple", "tablet"], "available": true}, {"name": "iPad Air", "desc": "First-generation small Apple tablet", "sku": "ATA0000", "price": 13.99, "tags": ["apple", "tablet"], "available": true}, {"name": "Samsung Galaxy A25", "desc": "Newest mobile phone from Samsung Galaxy mid-series (A)", "sku": "SPA0250", "price": 13.99, "tags": ["samsung", "phone"], "available": true}, {"name": "Samsung Galaxy A24", "desc": "Newest mobile phone from Samsung Galaxy mid-series (A)", "sku": "SPA0240", "price": 13.99, "tags": ["samsung", "phone"], "available": true}, {"name": "Samsung Galaxy A20", "desc": "Older mobile phone from Samsung Galaxy mid-series (A)", "sku": "SPA0200", "price": 13.99, "tags": ["samsung", "phone"], "available": true}, {"name": "Samsung Galaxy A15", "desc": "Old mobile phone from Samsung Galaxy mid-series (A)", "sku": "SPA0150", "price": 13.99, "tags": ["samsung", "phone"], "available": true}, {"name": "Samsung Galaxy S30", "desc": "Newest mobile phone from Samsung Galaxy high-end series (S)", "sku": "SPS3000", "price": 13.99, "tags": ["samsung", "phone"], "available": true}, {"name": "Samsung Galaxy S20", "desc": "Older mobile phone from Samsung Galaxy high-end series (S)", "sku": "SPS2000", "price": 13.99, "tags": ["samsung", "phone"], "available": true}, {"name": "Nothing Phone (3a)", "desc": "Newest mobile phone by breakout brand Nothing, known for their complex sci-fi-inspired designs.", "sku": "OPN0031", "price": 13.99, "tags": ["nothing", "phone"], "available": true}, {"name": "Nokia 1200", "desc": "Nokia phone from old storage, will break the ground if you drop it.", "sku": "NHN1200", "price": 13.99, "tags": ["nokia", "phone"], "available": true}, {"name": "Nokia 1110", "desc": "Nokia phone from old storage, will break the ground if you drop it.", "sku": "NHN1100", "price": 13.99, "tags": ["nokia", "phone"], "available": true}, {"name": "Samsung Galaxy Tab S10", "desc": "S10 tablet from Samsung", "sku": "SGT1910", "price": 13.99, "tags": ["samsung", "tablet"], "available": true}, {"name": "Samsung Galaxy Tab S7", "desc": "S7 tabler from Samsung", "sku": "SGT1907", "price": 13.99, "tags": ["samsung", "tablet"], "available": true}, {"name": "1 Plus Nord", "desc": "Popular phone from little-known brand 1+ (has many alternate spellings too)", "sku": "PPN0101", "price": 13.99, "tags": ["1 plus", "one plus", "1plus", "oneplus", "phone"], "available": true}, {"name": "Huawei P40", "desc": "Huawei P40 mobile phone", "sku": "HPN1640", "price": 13.99, "tags": ["huawei", "phone"], "available": true}, {"name": "Huawei Mate50", "desc": "Huawei P40 mobile phone", "sku": "HPM0050", "price": 13.99, "tags": ["huawei", "phone"], "available": true}]